{"docs_2020上_21世纪.md":"CpA2moKc","docs_2020上_今日，与我无关.md":"CFfG2fu0","docs_2020上_前方的路-笔记一.md":"CAolPMnb","docs_2020上_前方的路-笔记二.md":"BjAcPAkF","docs_2020上_单词笔记集.md":"tsALy8up","docs_2020上_又是别人的故事.md":"Bdtrfpe6","docs_2020上_影视感悟集.md":"Bq2AlTQB","docs_2020上_我所住的小屋.md":"PhMC2NI9","docs_2020上_我的人生.md":"BfQ4w7LH","docs_2020上_提升价值.md":"B9Qr_nee","docs_2020上_新生.md":"HDloDk10","docs_2020上_时间管理的七句话.md":"zN43sZpD","docs_2020上_最好的时光.md":"B4Hqf_Iy","docs_2020上_正义是客观的还是主观的.md":"EpIay_Ql","docs_2020上_砌一道高墙，拥着她入眠.md":"4tR7UIn3","docs_2020上_随笔集上.md":"D4NkLsRN","docs_2020上_随笔集下.md":"wJ8p5EBp","docs_2020下_import方式对webpack的tree-shaking影响.md":"MgwttRNM","docs_2020下_preset-env和polyfill及transform-runtime.md":"BaSgOMgU","docs_2021上_jest单元测试总结.md":"CQdYgrps","docs_2021上_js中__与__的优先级及实践.md":"CRg8ZvKe","docs_2021上_js中自执行函数的不同写法及内在原因.md":"Dzcf9dhu","docs_2021上_vue图片放大器的实现.md":"IC7lo_QN","docs_2021上_vue项目hash模式中记录滚动位置.md":"C7V6Q-fn","docs_2021上_前端优化之dns-prefetch和preconnect.md":"B9VipPkr","docs_2021上_认识一下css之美轮美奂的linear-gradient.md":"DAxToU6z","docs_2021上_记录hippy-vue开发遇到的问题.md":"DmZXhaew","docs_2021下_babel-core源码解析.md":"B-r1rMYA","docs_2021下_babel-generator源码解析.md":"DZE48XKk","docs_2021下_babel-parser源码解析.md":"Cr22iFQL","docs_2021下_babel-plugin-import原理.md":"B0KgqZYm","docs_2021下_babel-traverse源码解析.md":"jDucEZdh","docs_2021下_babel基础.md":"BP2GdviA","docs_2021下_process.env.node_env是如何被webpack替换的.md":"Bnbh2Gac","docs_2021下_rollup打包从0到1.md":"BzJKWspC","docs_2021下_vuerouter源码解析.md":"CQSxhzVT","docs_2021下_vuex源码解析.md":"DIru5Bpg","docs_2021下_关于源码阅读的思考.md":"BK7KkZbE","docs_2021下_在讲究用户体验的年代，如何高效的制作弹窗的动画效果.md":"B2-fb7u7","docs_2021下_异步任务调度器.md":"C_yu4byU","docs_2021下_探究007性能指标的实现方式（首屏加载时间的计算）.md":"ouzUpeIG","docs_2021下_浅析css-loader、style-loader原理.md":"D4izClnU","docs_2021下_浅析eslint原理.md":"-6PP8uT1","docs_2021下_浅析rollup打包原理.md":"BuNQQ6Yw","docs_2021下_浅析vue编译原理.md":"CCqgOVzf","docs_2021下_深入vueloader原理.md":"KfAFTZ7I","docs_2021下_深入webpack原理.md":"qvmle2Za","docs_2021下_深入webpack运行时原理.md":"BrMBr_BF","docs_2021下_深入解析vue2和vue3的响应式原理.md":"CKr8UTm7","docs_2021下_详解nodejs中的require.md":"nYdqTlHR","docs_2021下_详解unicode、utf-8、utf-16.md":"BXrNZogE","docs_2021下_谈谈generator和gensync.md":"DRR0FN2m","docs_2022上_babel入门.md":"BwJhY1iW","docs_2022上_cross-env是如何实现的.md":"CtoCQccK","docs_2022上_css和js会阻塞dom的解析渲染吗.md":"Csb4dA9k","docs_2022上_dns查询与递归迭代.md":"CLxtkOPP","docs_2022上_docker入门.md":"B5wJCHMv","docs_2022上_es6中的proxy和reflect.md":"DqowTZSe","docs_2022上_eslint配置一劳永逸.md":"BGqNPS0q","docs_2022上_gslb、tgw、stgw笔记.md":"DNgczCgr","docs_2022上_object.create方法及类的继承.md":"DXiZ9WTM","docs_2022上_reactfiber.md":"BJw_o9TV","docs_2022上_v8引擎介绍.md":"CHljuV5l","docs_2022上_vue2中的computed原理.md":"CVo1ndPU","docs_2022上_vue与react.md":"DeFwxO0n","docs_2022上_vue项目转ssr记录.md":"w1eEHH-q","docs_2022上_webpack-chain用法及原理.md":"B_-DpcH1","docs_2022上_一键部署dev项目.md":"Byy27GQO","docs_2022上_为form-create-designer增加table-slot.md":"DFUecEiG","docs_2022上_使用vuedraggable中的一些问题.md":"DsTiYjCx","docs_2022上_关于bem与css变量.md":"Djh7brFW","docs_2022上_关于vue实例的几个问题.md":"C6mitGcS","docs_2022上_几行代码实现koa的洋葱模型.md":"C_0FP8kX","docs_2022上_分层架构的理解与应用.md":"sPDzRt99","docs_2022上_前端安全.md":"OtFF6NSL","docs_2022上_前端工程化配置husky_commitlint.md":"DZ4uHW0s","docs_2022上_前端配置频繁更新怎么办.md":"B7srJyQk","docs_2022上_弹窗使用优化—函数式调用.md":"BeaizhfJ","docs_2022上_模拟滚动条.md":"DhW1O7_K","docs_2022上_浅析nprogress进度条的实现.md":"DQux-V_l","docs_2022上_浅析vant的下拉刷新组件.md":"CezL-4_Y","docs_2022上_浅析vue-cli原理.md":"DbH7krni","docs_2022上_用vscode插件解决alias跳转定义问题.md":"CX9vCLkB","docs_2022上_程序员的核心竞争力.md":"CB1iVqa6","docs_2022上_管理端表格组件提取.md":"Cj9nqQGR","docs_2022上_脚手架工具chalk用法及原理.md":"BOuteJKc","docs_2022上_脚手架工具commander用法及原理.md":"BFegjwIk","docs_2022上_运行跨域的chrome.md":"B8kHALZi","docs_2022上_那些年写过的企微机器人.md":"BsL17WIm","docs_2022下_h5项目一键转化uni-app项目的工具梳理.md":"C2SgvWNB","docs_2022下_ts笔记.md":"CPnUs0iU","docs_2022下_uni-app中改了一行代码，减少了3m打包体积.md":"DPOj5wIM","docs_2022下_uni-app分包优化——js分发.md":"BP5CwUNc","docs_2022下_uni-app分包优化——组件分发.md":"F_-BSs-7","docs_2022下_uni-app小程序中图片懒加载的适配方案.md":"DvmVM9TK","docs_2022下_uni-app小程序全局组件的优化.md":"imzQ_azZ","docs_2022下_uni-app小程序分包实践.md":"BwMinjzv","docs_2022下_uni-app小程序沉浸式导航.md":"Bo0vd_FH","docs_2022下_uni-app插件优化，提升3倍打包编译效率.md":"DKEBfaQA","docs_2022下_uni-app运行时原理.md":"CoaN9scD","docs_2022下_vite真香之路.md":"BcxlRlL1","docs_2022下_vue项目转uni-app的路由处理.md":"DnTVtv9R","docs_2022下_vue项目转uni-app问题记录——其他篇.md":"DITe_qW0","docs_2022下_vue项目转uni-app问题记录——构建篇.md":"CsS3hZRs","docs_2022下_vue项目转uni-app问题记录——样式篇.md":"DQetVUoN","docs_2022下_vue项目转uni-app问题记录——逻辑篇.md":"6OJw5js8","docs_2022下_一些正则.md":"DtiZ1mb1","docs_2022下_一种基于摩斯密码的页面加密方法（web和小程序）.md":"CeqdkskP","docs_2022下_公共子仓库自动打tag实现.md":"35MyUjzt","docs_2022下_写个webpack插件，查看项目文件依赖关系.md":"DNPiso9a","docs_2022下_前端国际化.md":"DVJL-KR0","docs_2022下_单测总结.md":"BMIjCX-J","docs_2022下_基于travis_docdash构建文档.md":"CdqEW7iR","docs_2022下_强化版的uni-app小程序持续集成.md":"DQqPS--P","docs_2022下_架构笔记.md":"Cu4TPQhP","docs_2022下_组件笔记.md":"B-CVC8wA","docs_2022下_赛程树样式重构.md":"CzuULsUe","docs_2022下_跨端工具链总结.md":"DhN0_7xa","docs_2023上_k8s概念.md":"BxmLyzKi","docs_2023上_pressui—基于uni-app的跨端组件库.md":"BQXnKgLd","docs_2023上_typescript中resolve参数为空时报错.md":"Dy_D7nw3","docs_2023上_一分钟了解husky原理.md":"CZBMkWXK","docs_2023上_代码重构之路.md":"BLhBzXsl","docs_2023上_聊天记录滚动锚定的实现.md":"Yqgm5ZhL","docs_2023上_自动化测试落地.md":"Cjmd6qNN","docs_2023上_随笔.md":"CvLbFbxu","docs_2023下_npm包漏洞探究.md":"CKIYuDU5","docs_2023下_pnpm迁移.md":"BcEBpOU6","docs_2023下_pressplus和elementlight组件库.md":"CDYpJyn1","docs_2023下_pressui应用于普通vue项目的实践.md":"DCBeSNUH","docs_2023下_pressui支持app.md":"3qPDjUwv","docs_2023下_pressui支持vue3.md":"CCVx7d5a","docs_2023下_pressui支持活动组件.md":"DKYkLy7_","docs_2023下_rosetta.md":"CoIBn2ys","docs_2023下_tdesign-mobile-vue暗黑模式的实现.md":"DzI1wR2A","docs_2023下_undefined与100比较.md":"BYxAYRnT","docs_2023下_修改ua.md":"STH3Qc0l","docs_2023下_关键词编译的类型提示.md":"BdZcgZ4u","docs_2023下_孪生项目的开发方式优化.md":"C6GAcO6J","docs_2024上_preprocess源码.md":"Bs0MITkF","docs_2024上_serviceworker理论与实践.md":"DbXZreMm","docs_2024上_uni-app在h5下的缓存机制.md":"CzSTS-C3","docs_2024上_专注力.md":"qpYCpWk5","docs_2024上_代码之丑-笔记.md":"DRAgkIEs","docs_2024上_后台-坑.md":"DoheY_Zv","docs_2024上_安全沙箱.md":"DsRzXa05","docs_2024上_技术领导力-笔记.md":"Bm1SE2Nb","docs_2024上_浏览器工作原理与实践-笔记.md":"D7RZxe6h","docs_2024上_海外部署记录.md":"D-opF12Y","docs_2024上_消极情绪.md":"ckXv2MaZ","docs_2024上_红包算法.md":"rNJzSiy_","docs_2024上_许式伟的架构课-笔记一.md":"B08s4GkF","docs_2024上_许式伟的架构课-笔记二.md":"DQWXpL2I","docs_2024上_设计模式之美-笔记.md":"s1cGoHqU","docs_2024上_阶段性人生目标.md":"CkXZkt9M","docs_2024下_colorpicker组件与色彩.md":"DVV27LSg","docs_2024下_react学习一.md":"BYvf6Ogq","docs_2024下_react学习二.md":"Hvdq6tbW","docs_2024下_tdesignminiprogram中cascader组件的性能优化.md":"D-_AWaVM","docs_2024下_书.md":"-prD0hOM","docs_2024下_递归partial.md":"pWo4QM_v","docs_2025上_5月感悟.md":"BUOjFtkI","docs_2025上_pmd-network.md":"DcHfgXd-","docs_2025上_ts类型体操.md":"58LrVx6K","docs_2025上_代码随想.md":"B0GdougK","docs_2025上_外包面试题.md":"DCsNdHkk","docs_2025下_ai-start.md":"LM8MlRO-","docs_2025下_ai需求.md":"CJHQVcgz","docs_2025下_business-core.md":"Df6tVHFe","docs_2025下_from-wx.md":"C4mTh3Fv","docs_2025下_git.md":"13v7kXTI","docs_2025下_hx-custom.md":"Bg_eEqV2","docs_2025下_h函数.md":"O67krVaK","docs_2025下_isolatedmodules-verbatimmodulesyntax.md":"BTH7KEoA","docs_2025下_mcp-agent-rag.md":"BV-dycdx","docs_2025下_notes-before.md":"D5W3kzxD","docs_2025下_promise-link.md":"Bn2TADwu","docs_2025下_stateless.md":"CC5SRrJB","docs_2025下_tdesign-miniprogram-monorepo.md":"DrKd9sM9","docs_2025下_tdesign-uniapp-article.md":"NW2f45Ed","docs_2025下_tdesign-uniapp-monorepo.md":"Ye7KgqY8","docs_2025下_tdesign-uniapp-other.md":"DiBbZ_E_","docs_2025下_tdesign-uniapp-publish.md":"OJLMWg1d","docs_2025下_tdesign.md":"D1CouMA6","docs_2025下_ti18n.md":"DUNaeAJi","docs_2025下_whistle-config.md":"BFfr1jdQ","docs_2025下_内存占用过高.md":"_TkKifPl","docs_2025下_工程师个人发展指南.md":"BMnYllSL","docs_2025下_最大似然估计.md":"BRyFsEiR","docs_2025下_深入浅出区块链.md":"C4hajF_I","docs_2025下_贝叶斯公式.md":"BpM1SIrX","docs_2025下_赛事横版支持任意页面关闭.md":"CvJopW3t","docs_2025下_频率学派与贝叶斯学派.md":"C8Mbapel","docs_张小龙_张小龙的微信盗梦十诫.md":"CqVwgddv","docs_张小龙_张小龙首次公开演讲.md":"CNOj7f0x","docs_张小龙_张小龙首次提出八大观点，诠释微信公众平台发展.md":"wm_Y6Kip","docs_张小龙_张小龙：如何把产品变简单.md":"DxO0YxP5","docs_算法_数组去重并排序.md":"DOc6MK3t","docs_算法_求长度最小的子数组.md":"2JjzR5TZ","index.md":"CWZ8rJzr","readme.md":"G4yhd7Xb"}
