{"docs_2020上_21世纪.md":"CJE2kSwu","docs_2020上_今日，与我无关.md":"BYclxnaO","docs_2020上_前方的路-笔记一.md":"BW1aVLRf","docs_2020上_前方的路-笔记二.md":"D8kGPGCu","docs_2020上_单词笔记集.md":"Cci33bbK","docs_2020上_又是别人的故事.md":"e-1WbJw4","docs_2020上_影视感悟集.md":"CP2OJ_ej","docs_2020上_我所住的小屋.md":"v53PIo3c","docs_2020上_我的人生.md":"BD6GBqGd","docs_2020上_提升价值.md":"tIJavrzz","docs_2020上_新生.md":"C7j4JR88","docs_2020上_时间管理的七句话.md":"7s0Z8x3q","docs_2020上_最好的时光.md":"B1kAguO5","docs_2020上_正义是客观的还是主观的.md":"BuBIiBNo","docs_2020上_砌一道高墙，拥着她入眠.md":"z8C5lZQm","docs_2020上_随笔集上.md":"DrLiWmMS","docs_2020上_随笔集下.md":"BwKOkwhO","docs_2020下_import方式对webpack的tree-shaking影响.md":"TeeABkC6","docs_2020下_preset-env和polyfill及transform-runtime.md":"DGHm-GFG","docs_2021上_jest单元测试总结.md":"B7RqwwGh","docs_2021上_js中__与__的优先级及实践.md":"w6A62trr","docs_2021上_js中自执行函数的不同写法及内在原因.md":"BU_vY80T","docs_2021上_vue图片放大器的实现.md":"nna4Vgi2","docs_2021上_vue项目hash模式中记录滚动位置.md":"DprfaJOI","docs_2021上_前端优化之dns-prefetch和preconnect.md":"DlxAaMdf","docs_2021上_认识一下css之美轮美奂的linear-gradient.md":"vtD2DRWM","docs_2021上_记录hippy-vue开发遇到的问题.md":"D18B8LnJ","docs_2021下_babel-core源码解析.md":"DpcGHetu","docs_2021下_babel-generator源码解析.md":"DcMtm-h2","docs_2021下_babel-parser源码解析.md":"DXESj8Xz","docs_2021下_babel-plugin-import原理.md":"BZnLjiHz","docs_2021下_babel-traverse源码解析.md":"CX01bZ6s","docs_2021下_babel基础.md":"BMLZHXI9","docs_2021下_process.env.node_env是如何被webpack替换的.md":"aOVN450Z","docs_2021下_rollup打包从0到1.md":"CaiY_krb","docs_2021下_vuerouter源码解析.md":"DVhp-hN5","docs_2021下_vuex源码解析.md":"y3u6w2Gh","docs_2021下_关于源码阅读的思考.md":"CoJFvynR","docs_2021下_在讲究用户体验的年代，如何高效的制作弹窗的动画效果.md":"DujOQA7s","docs_2021下_异步任务调度器.md":"5y4xRriT","docs_2021下_探究007性能指标的实现方式（首屏加载时间的计算）.md":"ITXwdW2r","docs_2021下_浅析css-loader、style-loader原理.md":"XhvuCGWz","docs_2021下_浅析eslint原理.md":"vQRi_TPy","docs_2021下_浅析rollup打包原理.md":"CdKYN5K0","docs_2021下_浅析vue编译原理.md":"BWZyngPw","docs_2021下_深入vueloader原理.md":"BB04yCCp","docs_2021下_深入webpack原理.md":"D-qQOkdo","docs_2021下_深入webpack运行时原理.md":"Dp-3rmcL","docs_2021下_深入解析vue2和vue3的响应式原理.md":"BfEiayk4","docs_2021下_详解nodejs中的require.md":"0XZCF8yi","docs_2021下_详解unicode、utf-8、utf-16.md":"B05HnCKM","docs_2021下_谈谈generator和gensync.md":"D9qfSB2N","docs_2022上_babel入门.md":"LUFuEV1s","docs_2022上_cross-env是如何实现的.md":"I9UALcVL","docs_2022上_css和js会阻塞dom的解析渲染吗.md":"DFu1hBIc","docs_2022上_dns查询与递归迭代.md":"WD6WuaOL","docs_2022上_docker入门.md":"Cs-hmJ78","docs_2022上_es6中的proxy和reflect.md":"BqGSJNP3","docs_2022上_eslint配置一劳永逸.md":"DwH5Q_Df","docs_2022上_gslb、tgw、stgw笔记.md":"1kBGsXMt","docs_2022上_object.create方法及类的继承.md":"B8skOfrc","docs_2022上_reactfiber.md":"BLa-gh0s","docs_2022上_v8引擎介绍.md":"CxMzWKRs","docs_2022上_vue2中的computed原理.md":"1ChS7p20","docs_2022上_vue与react.md":"CKO1jxQN","docs_2022上_vue项目转ssr记录.md":"D8WxkGA1","docs_2022上_webpack-chain用法及原理.md":"D5e-fSRA","docs_2022上_一键部署dev项目.md":"C4VU7E_x","docs_2022上_为form-create-designer增加table-slot.md":"D5CDrfBO","docs_2022上_使用vuedraggable中的一些问题.md":"DB21UhiE","docs_2022上_关于bem与css变量.md":"CRCqVX46","docs_2022上_关于vue实例的几个问题.md":"X1g17_Bc","docs_2022上_几行代码实现koa的洋葱模型.md":"DAB93emH","docs_2022上_分层架构的理解与应用.md":"D8kcxSnt","docs_2022上_前端安全.md":"CCxZOMFt","docs_2022上_前端工程化配置husky_commitlint.md":"DOGNhrDV","docs_2022上_前端配置频繁更新怎么办.md":"x41H0F7d","docs_2022上_弹窗使用优化—函数式调用.md":"j4-6i1yU","docs_2022上_模拟滚动条.md":"Cn-wZGOo","docs_2022上_浅析nprogress进度条的实现.md":"BbhMZ3xu","docs_2022上_浅析vant的下拉刷新组件.md":"CCfYQcQE","docs_2022上_浅析vue-cli原理.md":"CSfhpRRK","docs_2022上_用vscode插件解决alias跳转定义问题.md":"4bRnT2E_","docs_2022上_程序员的核心竞争力.md":"BxaOGDUS","docs_2022上_管理端表格组件提取.md":"Czo8IE9Y","docs_2022上_脚手架工具chalk用法及原理.md":"BtUU9hdm","docs_2022上_脚手架工具commander用法及原理.md":"4UbXb4-p","docs_2022上_运行跨域的chrome.md":"DenZX_OI","docs_2022上_那些年写过的企微机器人.md":"Djt3OFea","docs_2022下_h5项目一键转化uni-app项目的工具梳理.md":"ALIjtcKz","docs_2022下_ts笔记.md":"B-0IAq7h","docs_2022下_uni-app中改了一行代码，减少了3m打包体积.md":"ChyMnxKl","docs_2022下_uni-app分包优化——js分发.md":"BhkDQxVY","docs_2022下_uni-app分包优化——组件分发.md":"BnRJmFpP","docs_2022下_uni-app小程序中图片懒加载的适配方案.md":"C2CoL--I","docs_2022下_uni-app小程序全局组件的优化.md":"B0Shv47P","docs_2022下_uni-app小程序分包实践.md":"Pu1qz3de","docs_2022下_uni-app小程序沉浸式导航.md":"B9yUfySd","docs_2022下_uni-app插件优化，提升3倍打包编译效率.md":"-Lpxh5Dt","docs_2022下_uni-app运行时原理.md":"BWKcWb4B","docs_2022下_vite真香之路.md":"-XQhOyH7","docs_2022下_vue项目转uni-app的路由处理.md":"DzErPtZk","docs_2022下_vue项目转uni-app问题记录——其他篇.md":"BAmekyYl","docs_2022下_vue项目转uni-app问题记录——构建篇.md":"DxVwzWkS","docs_2022下_vue项目转uni-app问题记录——样式篇.md":"ebuzY-yH","docs_2022下_vue项目转uni-app问题记录——逻辑篇.md":"DmKxZASq","docs_2022下_一些正则.md":"Cq-7fd0Z","docs_2022下_一种基于摩斯密码的页面加密方法（web和小程序）.md":"Bfd-AK2Q","docs_2022下_公共子仓库自动打tag实现.md":"BbLMy6y2","docs_2022下_写个webpack插件，查看项目文件依赖关系.md":"BGpwI5ue","docs_2022下_前端国际化.md":"CpAmR1e9","docs_2022下_单测总结.md":"FRBPDwJj","docs_2022下_基于travis_docdash构建文档.md":"Cefn6Q0X","docs_2022下_强化版的uni-app小程序持续集成.md":"hoQ6chaj","docs_2022下_架构笔记.md":"5xN0v1t1","docs_2022下_组件笔记.md":"DcvtE7gq","docs_2022下_赛程树样式重构.md":"cnLqcG4V","docs_2022下_跨端工具链总结.md":"CeEsPEPT","docs_2023上_k8s概念.md":"B5EXWy6-","docs_2023上_pressui—基于uni-app的跨端组件库.md":"xTpmI94i","docs_2023上_typescript中resolve参数为空时报错.md":"BKxvIzEW","docs_2023上_一分钟了解husky原理.md":"C3U85hB1","docs_2023上_代码重构之路.md":"BvziB405","docs_2023上_聊天记录滚动锚定的实现.md":"Dgs1vrxA","docs_2023上_自动化测试落地.md":"C1zQlVYt","docs_2023上_随笔.md":"Cp3geMo4","docs_2023下_npm包漏洞探究.md":"DeuOukWb","docs_2023下_pnpm迁移.md":"BCznzdw4","docs_2023下_pressplus和elementlight组件库.md":"NsDBf50R","docs_2023下_pressui应用于普通vue项目的实践.md":"BtAubed0","docs_2023下_pressui支持app.md":"DWnOVGcX","docs_2023下_pressui支持vue3.md":"Dg6Ay6tg","docs_2023下_pressui支持活动组件.md":"umqHrgpv","docs_2023下_rosetta.md":"CDbLKYTJ","docs_2023下_tdesign-mobile-vue暗黑模式的实现.md":"D6DxZY3S","docs_2023下_undefined与100比较.md":"CIOTEUAk","docs_2023下_修改ua.md":"DTBlJdli","docs_2023下_关键词编译的类型提示.md":"Cdmz_1Dt","docs_2023下_孪生项目的开发方式优化.md":"BDkN0Nm5","docs_2024上_preprocess源码.md":"Bpcj9jvZ","docs_2024上_serviceworker理论与实践.md":"LhUZdKr_","docs_2024上_uni-app在h5下的缓存机制.md":"etfTf9wN","docs_2024上_专注力.md":"Bqml8Uo6","docs_2024上_代码之丑-笔记.md":"BzRqhJkK","docs_2024上_后台-坑.md":"BoUAZJrR","docs_2024上_安全沙箱.md":"BmNSuX3K","docs_2024上_技术领导力-笔记.md":"Dn3Z4FLP","docs_2024上_浏览器工作原理与实践-笔记.md":"Cni4RBrp","docs_2024上_海外部署记录.md":"CCfMUlnb","docs_2024上_消极情绪.md":"CRumMJ2a","docs_2024上_红包算法.md":"DVjK-m97","docs_2024上_许式伟的架构课-笔记一.md":"DxXOsBZK","docs_2024上_许式伟的架构课-笔记二.md":"Dj1PTYYM","docs_2024上_设计模式之美-笔记.md":"B8ryTp8R","docs_2024上_阶段性人生目标.md":"CmR-JdfO","docs_2024下_colorpicker组件与色彩.md":"CR84ipCu","docs_2024下_react学习一.md":"e6E2rWGf","docs_2024下_react学习二.md":"rf4uwIPb","docs_2024下_tdesignminiprogram中cascader组件的性能优化.md":"B-CvEP8Y","docs_2024下_书.md":"CuLwU1mG","docs_2024下_递归partial.md":"BQvD3go2","docs_2025上_5月感悟.md":"C5S2_Ffi","docs_2025上_pmd-network.md":"O4SJL97r","docs_2025上_ts类型体操.md":"CTX9TN9T","docs_2025上_代码随想.md":"Cs3vUF6D","docs_2025上_外包面试题.md":"CO5Xynso","docs_2025下_from-wx.md":"CkPR0u8z","docs_2025下_git.md":"CYO9-Wsg","docs_2025下_h函数.md":"p14bJoMj","docs_2025下_isolatedmodules-verbatimmodulesyntax.md":"Bc0B4dxj","docs_2025下_promise-link.md":"DhGPthgd","docs_2025下_tdesign-miniprogram-monorepo.md":"G94mCn-x","docs_2025下_tdesign-uniapp.md":"XSQzij95","docs_2025下_tdesign.md":"BVsAnMn5","docs_2025下_ti18n.md":"B53MEZ2S","docs_2025下_内存占用过高.md":"BH61m8pG","docs_2025下_工程师个人发展指南.md":"DgrjLX3a","docs_2025下_深入浅出区块链.md":"DKCsovPM","docs_张小龙_张小龙的微信盗梦十诫.md":"C11VqiHp","docs_张小龙_张小龙首次公开演讲.md":"Ddj8ZDE6","docs_张小龙_张小龙首次提出八大观点，诠释微信公众平台发展.md":"B2aPxuUD","docs_张小龙_张小龙：如何把产品变简单.md":"BKupR7fs","docs_算法_数组去重并排序.md":"CYnSHH5h","docs_算法_求长度最小的子数组.md":"aM3YvcIw","index.md":"CPK8fxiQ","readme.md":"ZLRT1_5E"}
