{"docs_2020上_21世纪.md":"BObX7ayQ","docs_2020上_今日，与我无关.md":"DPMa2LHk","docs_2020上_前方的路-笔记一.md":"DFZBjBy_","docs_2020上_前方的路-笔记二.md":"BMq-YqQA","docs_2020上_单词笔记集.md":"D7V8c4YK","docs_2020上_又是别人的故事.md":"DIQLsDi9","docs_2020上_影视感悟集.md":"BjcGJjma","docs_2020上_我所住的小屋.md":"DBLegpID","docs_2020上_我的人生.md":"DLqZKW91","docs_2020上_提升价值.md":"QXNO0FAa","docs_2020上_新生.md":"CzOHbAWC","docs_2020上_时间管理的七句话.md":"BnPSZB0R","docs_2020上_最好的时光.md":"D7dVimx4","docs_2020上_正义是客观的还是主观的.md":"7qIN618Y","docs_2020上_砌一道高墙，拥着她入眠.md":"Cz_TcPkx","docs_2020上_随笔集上.md":"DEt6U3y0","docs_2020上_随笔集下.md":"BZw42FRP","docs_2020下_import方式对webpack的tree-shaking影响.md":"D8DCPe-n","docs_2020下_preset-env和polyfill及transform-runtime.md":"DbZawqpI","docs_2021上_jest单元测试总结.md":"ByQgzp6N","docs_2021上_js中__与__的优先级及实践.md":"DVhwU1GM","docs_2021上_js中自执行函数的不同写法及内在原因.md":"DebX1w29","docs_2021上_vue图片放大器的实现.md":"BT2PYQz1","docs_2021上_vue项目hash模式中记录滚动位置.md":"D75qs0QD","docs_2021上_前端优化之dns-prefetch和preconnect.md":"CDdjU27V","docs_2021上_认识一下css之美轮美奂的linear-gradient.md":"DELHWiu3","docs_2021上_记录hippy-vue开发遇到的问题.md":"KDbIgcBu","docs_2021下_babel-core源码解析.md":"BCe7OgqO","docs_2021下_babel-generator源码解析.md":"Cs3oGsM4","docs_2021下_babel-parser源码解析.md":"CK3Y-mSn","docs_2021下_babel-plugin-import原理.md":"DOWZZnPe","docs_2021下_babel-traverse源码解析.md":"BlK6DXo5","docs_2021下_babel基础.md":"uMEz3jq9","docs_2021下_process.env.node_env是如何被webpack替换的.md":"CNF2danc","docs_2021下_rollup打包从0到1.md":"D1oTYvVY","docs_2021下_vuerouter源码解析.md":"-EhIa7Nd","docs_2021下_vuex源码解析.md":"DUNtyz2R","docs_2021下_关于源码阅读的思考.md":"DqUdv6AW","docs_2021下_在讲究用户体验的年代，如何高效的制作弹窗的动画效果.md":"DDPg3h1x","docs_2021下_异步任务调度器.md":"CL-mJ_zV","docs_2021下_探究007性能指标的实现方式（首屏加载时间的计算）.md":"DpYHl_A_","docs_2021下_浅析css-loader、style-loader原理.md":"e4VgNYQP","docs_2021下_浅析eslint原理.md":"BZUBYdJR","docs_2021下_浅析rollup打包原理.md":"HBWIIgjW","docs_2021下_浅析vue编译原理.md":"C4dwZY80","docs_2021下_深入vueloader原理.md":"DrazR6CR","docs_2021下_深入webpack原理.md":"CQxOZnT6","docs_2021下_深入webpack运行时原理.md":"CPFAQIIw","docs_2021下_深入解析vue2和vue3的响应式原理.md":"DqiDZnAu","docs_2021下_详解nodejs中的require.md":"DVRUNa5N","docs_2021下_详解unicode、utf-8、utf-16.md":"DXQ9oW1D","docs_2021下_谈谈generator和gensync.md":"DdC4mAAi","docs_2022上_babel入门.md":"BUndwJyI","docs_2022上_cross-env是如何实现的.md":"NRHK-Brz","docs_2022上_css和js会阻塞dom的解析渲染吗.md":"BpRQm2TF","docs_2022上_dns查询与递归迭代.md":"DVKasHfo","docs_2022上_docker入门.md":"B9zaNL-t","docs_2022上_es6中的proxy和reflect.md":"CcSgsd9a","docs_2022上_eslint配置一劳永逸.md":"D-HjW2Vc","docs_2022上_gslb、tgw、stgw笔记.md":"BG49KQvA","docs_2022上_object.create方法及类的继承.md":"sFCLFW9u","docs_2022上_reactfiber.md":"CUn-fc3a","docs_2022上_v8引擎介绍.md":"BQ48I5Sk","docs_2022上_vue2中的computed原理.md":"D8-_iL0n","docs_2022上_vue与react.md":"BNFL3Zz1","docs_2022上_vue项目转ssr记录.md":"CY6v0J66","docs_2022上_webpack-chain用法及原理.md":"DOuSq2ts","docs_2022上_一键部署dev项目.md":"BUst2xkr","docs_2022上_为form-create-designer增加table-slot.md":"BUYboJTM","docs_2022上_使用vuedraggable中的一些问题.md":"iXZGBWBe","docs_2022上_关于bem与css变量.md":"DVx2oJpG","docs_2022上_关于vue实例的几个问题.md":"CqbWofcS","docs_2022上_几行代码实现koa的洋葱模型.md":"D2tKYw_M","docs_2022上_分层架构的理解与应用.md":"BJw1iB5T","docs_2022上_前端安全.md":"xCnLJ9vQ","docs_2022上_前端工程化配置husky_commitlint.md":"DmiX7IGh","docs_2022上_前端配置频繁更新怎么办.md":"B5SMZmmd","docs_2022上_弹窗使用优化—函数式调用.md":"CKNGu-Dk","docs_2022上_模拟滚动条.md":"CEG4dbST","docs_2022上_浅析nprogress进度条的实现.md":"Ca20Agaq","docs_2022上_浅析vant的下拉刷新组件.md":"DDZ_4hUC","docs_2022上_浅析vue-cli原理.md":"DKRa-fan","docs_2022上_用vscode插件解决alias跳转定义问题.md":"DDorG_ct","docs_2022上_程序员的核心竞争力.md":"D7OitDDw","docs_2022上_管理端表格组件提取.md":"momscdmt","docs_2022上_脚手架工具chalk用法及原理.md":"DeRTBSvj","docs_2022上_脚手架工具commander用法及原理.md":"CFY0WUwv","docs_2022上_那些年写过的企微机器人.md":"BhSz4otT","docs_2022下_h5项目一键转化uni-app项目的工具梳理.md":"D_vUSv3P","docs_2022下_ts笔记.md":"eHgkjukd","docs_2022下_uni-app中改了一行代码，减少了3m打包体积.md":"Coj4bfKL","docs_2022下_uni-app分包优化——js分发.md":"2cWLZ14E","docs_2022下_uni-app分包优化——组件分发.md":"BL2AWgfU","docs_2022下_uni-app小程序中图片懒加载的适配方案.md":"CFXuGTKY","docs_2022下_uni-app小程序全局组件的优化.md":"xOrVR_Xa","docs_2022下_uni-app小程序分包实践.md":"C1IYUp9z","docs_2022下_uni-app小程序沉浸式导航.md":"F_QCqOFZ","docs_2022下_uni-app插件优化，提升3倍打包编译效率.md":"B4SQO56t","docs_2022下_uni-app运行时原理.md":"C1U82SHY","docs_2022下_vite真香之路.md":"DxNLSozB","docs_2022下_vue项目转uni-app的路由处理.md":"DGJHmXVH","docs_2022下_vue项目转uni-app问题记录——其他篇.md":"D00QXuYA","docs_2022下_vue项目转uni-app问题记录——构建篇.md":"MTnoFHlC","docs_2022下_vue项目转uni-app问题记录——样式篇.md":"CLytQUB5","docs_2022下_vue项目转uni-app问题记录——逻辑篇.md":"MMy3_KWk","docs_2022下_一些正则.md":"DaKWjQvj","docs_2022下_一种基于摩斯密码的页面加密方法（web和小程序）.md":"BSXacW5q","docs_2022下_公共子仓库自动打tag实现.md":"Cy4_4LGD","docs_2022下_写个webpack插件，查看项目文件依赖关系.md":"CUASndYR","docs_2022下_前端国际化.md":"mzUYZjCf","docs_2022下_基于travis_docdash构建文档.md":"4MaTWBKA","docs_2022下_强化版的uni-app小程序持续集成.md":"BaB4k_8I","docs_2022下_架构笔记.md":"BEoo9KBd","docs_2022下_组件笔记.md":"CpLqyqjK","docs_2022下_赛程树样式重构.md":"DDm7uHAG","docs_2022下_跨端工具链总结.md":"Cpw12ZpM","docs_2023上_k8s概念.md":"BHHF6K9t","docs_2023上_pressui—基于uni-app的跨端组件库.md":"CTRQgs25","docs_2023上_qq小程序组件加载失败分析.md":"CPC18JCR","docs_2023上_一分钟了解husky原理.md":"jBOsgRRl","docs_2023上_代码重构之路.md":"Xe0EpBAf","docs_2023上_聊天记录滚动锚定的实现.md":"jRWVhN_R","docs_2023上_自动化测试落地.md":"D31glwYT","docs_2023上_随笔.md":"D0JLZqZS","docs_2023下_npm包漏洞探究.md":"B3fGE9Ju","docs_2023下_pnpm迁移.md":"CPXF4xSE","docs_2023下_pressplus和elementlight组件库.md":"DzKC6tNo","docs_2023下_pressui应用于普通vue项目的实践.md":"CJFGL0_x","docs_2023下_pressui支持app.md":"DxeizXj6","docs_2023下_pressui支持vue3.md":"CagZbJ-S","docs_2023下_pressui支持活动组件.md":"BO-gVuDM","docs_2023下_tdesign-mobile-vue暗黑模式的实现.md":"8tf7-MA6","docs_2023下_关键词编译的类型提示.md":"B_4NuSdC","docs_2023下_孪生项目的开发方式优化.md":"Dan6F31o","docs_2023下_小程序ci升级.md":"Bv2pTVbx","docs_2024上_10分钟看完vue3工程适配.md":"e-rrTdfl","docs_2024上_preprocess源码.md":"cXLVzDbN","docs_2024上_pressui支持支付宝小程序.md":"DjSIBAuK","docs_2024上_serviceworker理论与实践.md":"CaCw0KPq","docs_2024上_uni-app在h5下的缓存机制.md":"DDnYUb1T","docs_2024上_代码之丑-笔记.md":"j0QKlCOH","docs_2024上_后台-坑.md":"CWzRR8Ch","docs_2024上_基于uni-app项目的性能优化.md":"BPYK8-3t","docs_2024上_浏览器工作原理与实践-笔记.md":"BJMjLtml","docs_2024上_用户体验优化-无感登录webview.md":"D-GCwLfu","docs_2024上_迁移库引用.md":"HEL81FcA","docs_2024上_阶段性人生目标.md":"BpP98zUl","docs_2024下_colorpicker组件与色彩.md":"C4L7cQmV","docs_2024下_pix-ui-aegis.md":"BfcZY_8T","docs_2024下_pix-ui为什么用react.md":"BsT3753a","docs_2024下_pix-ui网络请求和登录态.md":"e-3rDsOO","docs_2024下_react学习.md":"CRL6htvk","docs_2024下_tdesignminiprogram中cascader组件的性能优化.md":"BtalUo6g","docs_2024下_vite版本的组件分发插件.md":"D2Tn0nex","docs_2024下_vite版本的脚本分发插件.md":"Nb5IPD4O","docs_2024下_vue3升级总结.md":"BMZ_04Cc","docs_2024下_书.md":"BOtM3iOa","docs_2024下_基于uni-app的小程序插件.md":"D2gcO0Lc","docs_2024下_小程序登录体验优化.md":"DXbdwfs9","docs_2024下_用户体验优化总结.md":"CrzNydDX","docs_2025上_element-ui组件库升级.md":"D7IMMKa6","docs_2025上_plugin-light和press-ui等基础库同步.md":"D6V7plHy","docs_2025上_tailwindcss应用.md":"B2lS7b1A","docs_2025上_tailwindcss细节.md":"D_dN1dYI","docs_2025上_vant组件库升级.md":"BvRbftRF","docs_2025上_代码规范总结.md":"DUkKbbHc","docs_2025上_代码随想.md":"DTBESTS_","docs_2025上_外包面试题.md":"uAyz2AGK","docs_2025上_项目优化.md":"CcxZMbvG","docs_api-examples.md":"DECtbxIT","docs_markdown-examples.md":"DMZgPDvz","docs_张小龙_张小龙的微信盗梦十诫.md":"BZAfFJvu","docs_张小龙_张小龙首次公开演讲.md":"DdHkK9Me","docs_张小龙_张小龙首次提出八大观点，诠释微信公众平台发展.md":"U7T6Prwh","docs_张小龙_张小龙：如何把产品变简单.md":"B46QogC5","index.md":"Broq_Q-L","readme.md":"BRV5vpx_"}
